ldbcache.py
ldbcache-0.0.0.dist-info/LICENCE
ldbcache-0.0.0.dist-info/METADATA
ldbcache-0.0.0.dist-info/WHEEL
ldbcache-0.0.0.dist-info/top_level.txt
ldbcache-0.0.0.dist-info/RECORD
