Metadata-Version: 2.1
Name: ldbcache
Version: 0.0.0
Summary: Local dabatase caching.
Home-page: https://github.com/Exahilosys/ldbcache
Author: Exahilosys
Author-email: UNKNOWN
License: MIT
Platform: UNKNOWN
Requires-Dist: pathing
